{
    "sourceFile": "server.js",
    "activeCommit": 0,
    "commits": [
        {
            "activePatchIndex": 3,
            "patches": [
                {
                    "date": 1621955528771,
                    "content": "Index: \n===================================================================\n--- \n+++ \n"
                },
                {
                    "date": 1621955536052,
                    "content": "Index: \n===================================================================\n--- \n+++ \n@@ -9,9 +9,16 @@\n \n app.use(routingAPI);\n app.use(express.static('./public'));\n \n-initDB().then(() => {\n+(async() => {\n+    await initDB();\n     app.listen(PORT, () => {\n         console.info(`Escuchando en puerto ${PORT}`);\n\\ No newline at end of file\n     });\n-});\n+})();\n+\n+// initDB().then(() => {\n+//   app.listen(PORT, () => {\n+//     console.info(`Escuchando en puerto ${PORT}`);\n+//   });\n+// });\n\\ No newline at end of file\n"
                },
                {
                    "date": 1622026392931,
                    "content": "Index: \n===================================================================\n--- \n+++ \n@@ -9,14 +9,12 @@\n \n app.use(routingAPI);\n app.use(express.static('./public'));\n \n-(async() => {\n-    await initDB();\n-    app.listen(PORT, () => {\n-        console.info(`Escuchando en puerto ${PORT}`);\n-    });\n-})();\n+initDB();\n+app.listen(PORT, () => {\n+    console.info(`Escuchando en puerto ${PORT}`);\n+});\n \n // initDB().then(() => {\n //   app.listen(PORT, () => {\n //     console.info(`Escuchando en puerto ${PORT}`);\n"
                },
                {
                    "date": 1622026486486,
                    "content": "Index: \n===================================================================\n--- \n+++ \n@@ -9,12 +9,14 @@\n \n app.use(routingAPI);\n app.use(express.static('./public'));\n \n-initDB();\n-app.listen(PORT, () => {\n-    console.info(`Escuchando en puerto ${PORT}`);\n-});\n+(async() => {\n+    await initDB();\n+    app.listen(PORT, () => {\n+        console.info(`Escuchando en puerto ${PORT}`);\n+    });\n+})();\n \n // initDB().then(() => {\n //   app.listen(PORT, () => {\n //     console.info(`Escuchando en puerto ${PORT}`);\n"
                }
            ],
            "date": 1621955528771,
            "name": "Commit-0",
            "content": "const express = require('express');\nconst { PORT } = require('./src/config');\nconst routingAPI = require('./src/handlers');\nconst { initDB } = require('./src/database');\n\nconst app = express();\n\napp.use(express.json());\n\napp.use(routingAPI);\napp.use(express.static('./public'));\n\ninitDB().then(() => {\n    app.listen(PORT, () => {\n        console.info(`Escuchando en puerto ${PORT}`);\n    });\n});"
        }
    ]
}